README.md
setup.cfg
setup.py
transfer_nlp/__init__.py
transfer_nlp.egg-info/PKG-INFO
transfer_nlp.egg-info/SOURCES.txt
transfer_nlp.egg-info/dependency_links.txt
transfer_nlp.egg-info/requires.txt
transfer_nlp.egg-info/top_level.txt
transfer_nlp/common/__init__.py
transfer_nlp/common/tokenizers.py
transfer_nlp/common/utils.py
transfer_nlp/embeddings/__init__.py
transfer_nlp/embeddings/embeddings.py
transfer_nlp/embeddings/utils.py
transfer_nlp/loaders/__init__.py
transfer_nlp/loaders/loaders.py
transfer_nlp/loaders/vectorizers.py
transfer_nlp/loaders/vocabulary.py
transfer_nlp/plugins/__init__.py
transfer_nlp/plugins/config.py
transfer_nlp/plugins/helpers.py
transfer_nlp/plugins/metrics.py
transfer_nlp/plugins/predictors.py
transfer_nlp/plugins/regularizers.py
transfer_nlp/plugins/reporters.py
transfer_nlp/plugins/trainer_abc.py
transfer_nlp/plugins/trainers.py
transfer_nlp/runner/__init__.py
transfer_nlp/runner/experiment_runner.py