Metadata-Version: 2.1
Name: transfer-nlp
Version: 0.1.6
Summary: NLP library designed for flexible research and development
Home-page: https://github.com/feedly/transfer-nlp
Author: Peter Martigny
Author-email: peter.martigny@gmail.com
License: MIT
Download-URL: https://github.com/feedly/transfer-nlp/archive/v0.1.6.tar.gz
Keywords: NLP,transfer learning,language models,NLU
Platform: UNKNOWN
Classifier: Development Status :: 3 - Alpha
Classifier: Intended Audience :: Science/Research
Classifier: Topic :: Scientific/Engineering :: Artificial Intelligence
Classifier: License :: OSI Approved :: MIT License
Classifier: Programming Language :: Python :: 3.6
Provides-Extra: torch
